README.md
setup.py
kharon/command_line.py
kharon/ferry.py
kharon/hardware.py
kharon/makeproject.py
kharon/template.ino
kharon/types.py
kharon.egg-info/PKG-INFO
kharon.egg-info/SOURCES.txt
kharon.egg-info/dependency_links.txt
kharon.egg-info/not-zip-safe
kharon.egg-info/top_level.txt
kharon/projecttemplates/__init__.py
kharon/projecttemplates/command.py
kharon/projecttemplates/devices.py
kharon/projecttemplates/master.py
kharon/projecttemplates/settings.py