Metadata-Version: 1.0
Name: kharon
Version: 0.1.2.6
Summary: Simplifying hardware/iot development with a Django style batteries-included framework
Home-page: https://github.com/RedRussianBear/kharon
Author: Mikhail Khrenov, Sahil Kochar, Shriyash Upadhyay
Author-email: mkhrenov34@gmail.com
License: BSD
Platform: UNKNOWN
